mv/__init__.py
mv-0.0.3.dist-info/LICENSE
mv-0.0.3.dist-info/METADATA
mv-0.0.3.dist-info/WHEEL
mv-0.0.3.dist-info/top_level.txt
mv-0.0.3.dist-info/RECORD
