Metadata-Version: 2.1
Name: mv
Version: 0.0.3
Summary: Parsing search terms
Home-page: https://github.com/thorwhalen/ut/tree/master/parse/parse_search_terms.py
Author: Thor Whalen
License: apache-2.0
Platform: any
License-File: LICENSE
